{
  "entrypoints": [
    "main"
  ],
  "origins": {
    "237": [
      237
    ],
    "674": [
      61,
      401,
      869,
      674
    ],
    "17896441": [
      674,
      869,
      401
    ],
    "main": [
      869,
      973,
      792
    ],
    "runtime~main": [
      792,
      869,
      973
    ],
    "1162ba6f": [
      574
    ],
    "125f3ada": [
      858
    ],
    "143da618": [
      343
    ],
    "1cda0596": [
      74
    ],
    "1f391b9e": [
      674,
      869,
      61
    ],
    "27310fc7": [
      222
    ],
    "393be207": [
      134
    ],
    "41b45870": [
      878
    ],
    "5e95c892": [
      647
    ],
    "6ac07d04": [
      84
    ],
    "935f2afb": [
      581
    ],
    "a7bd4aaa": [
      98
    ],
    "a94703ab": [
      869,
      48
    ],
    "c4f5d8e4": [
      869,
      634
    ],
    "cf7d2b6f": [
      917
    ],
    "d9729ef9": [
      148
    ],
    "e2476a2c": [
      275
    ],
    "e50b7e2c": [
      354
    ],
    "f5dbe7ad": [
      13
    ],
    "styles": [
      48,
      61,
      401,
      634,
      674,
      792,
      973,
      869
    ]
  },
  "assets": {
    "13": {
      "js": [
        {
          "file": "assets/js/f5dbe7ad.3743688e.js",
          "hash": "359b0d98a477b45c",
          "publicPath": "/assets/js/f5dbe7ad.3743688e.js"
        }
      ]
    },
    "48": {
      "js": [
        {
          "file": "assets/js/a94703ab.5e7a3c39.js",
          "hash": "41015f9732b9485e",
          "publicPath": "/assets/js/a94703ab.5e7a3c39.js"
        }
      ]
    },
    "61": {
      "js": [
        {
          "file": "assets/js/1f391b9e.d60e0eb7.js",
          "hash": "cc7259269fccb5fa",
          "publicPath": "/assets/js/1f391b9e.d60e0eb7.js"
        }
      ]
    },
    "74": {
      "js": [
        {
          "file": "assets/js/1cda0596.92a606c0.js",
          "hash": "85f9c9d80c602d71",
          "publicPath": "/assets/js/1cda0596.92a606c0.js"
        }
      ]
    },
    "84": {
      "js": [
        {
          "file": "assets/js/6ac07d04.265ed00d.js",
          "hash": "f54bbeeb95fa358e",
          "publicPath": "/assets/js/6ac07d04.265ed00d.js"
        }
      ]
    },
    "98": {
      "js": [
        {
          "file": "assets/js/a7bd4aaa.e54b7b51.js",
          "hash": "774a001968f69add",
          "publicPath": "/assets/js/a7bd4aaa.e54b7b51.js"
        }
      ]
    },
    "134": {
      "js": [
        {
          "file": "assets/js/393be207.afa3e47e.js",
          "hash": "71c488b8025a08d7",
          "publicPath": "/assets/js/393be207.afa3e47e.js"
        }
      ]
    },
    "148": {
      "js": [
        {
          "file": "assets/js/d9729ef9.356b1762.js",
          "hash": "b0b6871f272fb335",
          "publicPath": "/assets/js/d9729ef9.356b1762.js"
        }
      ]
    },
    "222": {
      "js": [
        {
          "file": "assets/js/27310fc7.550bf97a.js",
          "hash": "638a23878413d9ba",
          "publicPath": "/assets/js/27310fc7.550bf97a.js"
        }
      ]
    },
    "237": {
      "js": [
        {
          "file": "assets/js/237.40a31006.js",
          "hash": "aadf8cfbb95d79be",
          "publicPath": "/assets/js/237.40a31006.js"
        }
      ]
    },
    "275": {
      "js": [
        {
          "file": "assets/js/e2476a2c.aaec0f14.js",
          "hash": "0e7c702e67614700",
          "publicPath": "/assets/js/e2476a2c.aaec0f14.js"
        }
      ]
    },
    "343": {
      "js": [
        {
          "file": "assets/js/143da618.5ca4d9ae.js",
          "hash": "31f996d6b187b498",
          "publicPath": "/assets/js/143da618.5ca4d9ae.js"
        }
      ]
    },
    "354": {
      "js": [
        {
          "file": "assets/js/e50b7e2c.d32fdeec.js",
          "hash": "39c2445500a6e950",
          "publicPath": "/assets/js/e50b7e2c.d32fdeec.js"
        }
      ]
    },
    "401": {
      "js": [
        {
          "file": "assets/js/17896441.39fc7d29.js",
          "hash": "4eb15a64ec409c70",
          "publicPath": "/assets/js/17896441.39fc7d29.js"
        }
      ]
    },
    "574": {
      "js": [
        {
          "file": "assets/js/1162ba6f.53904146.js",
          "hash": "9d050b539069504b",
          "publicPath": "/assets/js/1162ba6f.53904146.js"
        }
      ]
    },
    "581": {
      "js": [
        {
          "file": "assets/js/935f2afb.5fd5088a.js",
          "hash": "db82a339bf6cfeec",
          "publicPath": "/assets/js/935f2afb.5fd5088a.js"
        }
      ]
    },
    "634": {
      "js": [
        {
          "file": "assets/js/c4f5d8e4.bdd0ab82.js",
          "hash": "a2af4cfd64cac479",
          "publicPath": "/assets/js/c4f5d8e4.bdd0ab82.js"
        }
      ]
    },
    "647": {
      "js": [
        {
          "file": "assets/js/5e95c892.ed777009.js",
          "hash": "3bd2f22e5dda5849",
          "publicPath": "/assets/js/5e95c892.ed777009.js"
        }
      ]
    },
    "674": {
      "js": [
        {
          "file": "assets/js/674.2ec01f1e.js",
          "hash": "181b41077090b52f",
          "publicPath": "/assets/js/674.2ec01f1e.js"
        }
      ]
    },
    "792": {
      "js": [
        {
          "file": "assets/js/main.392d7ddb.js",
          "hash": "6bb31386d1280aad",
          "publicPath": "/assets/js/main.392d7ddb.js"
        }
      ]
    },
    "858": {
      "js": [
        {
          "file": "assets/js/125f3ada.5b2d405d.js",
          "hash": "360d1c349bf2c7c8",
          "publicPath": "/assets/js/125f3ada.5b2d405d.js"
        }
      ]
    },
    "869": {
      "css": [
        {
          "file": "assets/css/styles.345bffd7.css",
          "hash": "10da40d9c78464ce",
          "publicPath": "/assets/css/styles.345bffd7.css"
        }
      ]
    },
    "878": {
      "js": [
        {
          "file": "assets/js/41b45870.5430d47e.js",
          "hash": "11240ec13eece9d5",
          "publicPath": "/assets/js/41b45870.5430d47e.js"
        }
      ]
    },
    "917": {
      "js": [
        {
          "file": "assets/js/cf7d2b6f.7cdd7e8e.js",
          "hash": "6a0078ad7ea5b988",
          "publicPath": "/assets/js/cf7d2b6f.7cdd7e8e.js"
        }
      ]
    },
    "973": {
      "js": [
        {
          "file": "assets/js/runtime~main.d8bbe362.js",
          "hash": "8a9dea8dc76cbbfb",
          "publicPath": "/assets/js/runtime~main.d8bbe362.js"
        }
      ]
    }
  }
}